tree_sitter_rsml/__init__.py
tree_sitter_rsml/__init__.pyi
tree_sitter_rsml/_binding.pyd
tree_sitter_rsml/binding.c
tree_sitter_rsml/py.typed
tree_sitter_rsml-0.1.13.dist-info/METADATA
tree_sitter_rsml-0.1.13.dist-info/WHEEL
tree_sitter_rsml-0.1.13.dist-info/top_level.txt
tree_sitter_rsml-0.1.13.dist-info/RECORD
