Metadata-Version: 2.4
Name: tree-sitter-rsml
Version: 0.1.13
Summary: Rsml grammar for tree-sitter
Author: Cameron P Campbell
License: MIT
Project-URL: Homepage, https://github.com/tree-sitter/tree-sitter-rsml
Keywords: incremental,parsing,tree-sitter,rsml
Classifier: Intended Audience :: Developers
Classifier: Topic :: Software Development :: Compilers
Classifier: Topic :: Text Processing :: Linguistic
Classifier: Typing :: Typed
Requires-Python: >=3.10
Provides-Extra: core
Requires-Dist: tree-sitter~=0.24; extra == "core"
